flask_googlecharts/__init__.py
flask_googlecharts/utils.py
flask_googlecharts/static/charts.init.js
flask_googlecharts/templates/chart.html
flask_googlecharts/templates/init.js
Flask_GoogleCharts-0.1.0.dist-info/LICENSE
Flask_GoogleCharts-0.1.0.dist-info/METADATA
Flask_GoogleCharts-0.1.0.dist-info/WHEEL
Flask_GoogleCharts-0.1.0.dist-info/top_level.txt
Flask_GoogleCharts-0.1.0.dist-info/RECORD
